LICENSE
README.md
setup.py
ban/KAN.py
ban/KANLayer.py
ban/LBFGS.py
ban/Symbolic_KANLayer.py
ban/__init__.py
ban/spline.py
ban/utils.py
pyban1.egg-info/PKG-INFO
pyban1.egg-info/SOURCES.txt
pyban1.egg-info/dependency_links.txt
pyban1.egg-info/top_level.txt