Metadata-Version: 2.1
Name: pyban1
Version: 0.0.1
Summary: Bamidele Awojoyogbe Networks
Home-page: UNKNOWN
Author: Jeremiah Ayanda
Author-email: olumaintain619@gmail.com
License: UNKNOWN
Platform: UNKNOWN
Classifier: Programming Language :: Python :: 3
Classifier: License :: OSI Approved :: MIT License
Classifier: Operating System :: OS Independent
Requires-Python: >=3.6
License-File: LICENSE
